src/__init__.py
src/deskpanel.py
deskpanel-0.1.0.dist-info/LICENSE.txt
deskpanel-0.1.0.dist-info/METADATA
deskpanel-0.1.0.dist-info/WHEEL
deskpanel-0.1.0.dist-info/top_level.txt
deskpanel-0.1.0.dist-info/RECORD
